koios/__init__.py
koios/datagen.py
koios/perceptron.py
koios-0.0.1.dist-info/METADATA
koios-0.0.1.dist-info/RECORD
koios-0.0.1.dist-info/WHEEL
koios-0.0.1.dist-info/top_level.txt
koios-0.0.1.dist-info/.ipynb_checkpoints/SOURCES-checkpoint.txt
