Metadata-Version: 2.1
Name: koios
Version: 0.0.1
Summary: Machine learning in Python!
Home-page: http://github.com/somapaul/koios
Author: Paul A. Soma, Jr.
Author-email: somapaul@msu.edu
License: MIT
Platform: UNKNOWN
Classifier: Programming Language :: Python :: 3
Classifier: License :: OSI Approved :: MIT License
Classifier: Operating System :: OS Independent
